{
	"name": "Activity4",
	"layers": [
		{
			"name": "Background",
			"overriden": 0,
			"subLayers": [],
			"instances": [
				{
					"type": "CloudBackground",
					"properties": {
						"initially-visible": true,
						"initial-animation": "Animation 1",
						"initial-frame": 0,
						"enable-collisions": true,
						"live-preview": false
					},
					"uid": 406,
					"instanceVariables": {},
					"behaviors": {
						"Tween": {
							"properties": {
								"enabled": true
							}
						}
					},
					"world": {
						"x": 960,
						"y": 261,
						"width": 2102,
						"height": 1662,
						"originX": 0.5,
						"originY": 0.5,
						"color": [
							1,
							1,
							1,
							1
						],
						"angle": 0,
						"zElevation": 0
					}
				},
				{
					"type": "bars",
					"properties": {
						"initially-visible": true,
						"initial-animation": "Animation 1",
						"initial-frame": 0,
						"enable-collisions": true,
						"live-preview": false
					},
					"uid": 413,
					"instanceVariables": {},
					"behaviors": {
						"Tween": {
							"properties": {
								"enabled": true
							}
						}
					},
					"world": {
						"x": 960,
						"y": 44,
						"width": 1000,
						"height": 54,
						"originX": 0.5,
						"originY": 0.5,
						"color": [
							1,
							1,
							1,
							1
						],
						"angle": 0,
						"zElevation": 0
					}
				},
				{
					"type": "q1",
					"properties": {
						"initially-visible": true,
						"initial-animation": "Animation 1",
						"initial-frame": 3,
						"enable-collisions": true,
						"live-preview": false
					},
					"uid": 415,
					"instanceVariables": {},
					"behaviors": {
						"Tween": {
							"properties": {
								"enabled": true
							}
						}
					},
					"world": {
						"x": 750,
						"y": 617,
						"width": 1722,
						"height": 325,
						"originX": 0.5,
						"originY": 0.5,
						"color": [
							1,
							1,
							1,
							1
						],
						"angle": 0,
						"zElevation": 0
					}
				},
				{
					"type": "Correct2",
					"properties": {
						"initially-visible": false,
						"initial-animation": "Animation 1",
						"initial-frame": 0,
						"enable-collisions": true,
						"live-preview": false
					},
					"uid": 423,
					"instanceVariables": {},
					"behaviors": {},
					"world": {
						"x": 553.4114773068217,
						"y": 636.8394241224617,
						"width": 285.6504545250741,
						"height": 173.7513160219156,
						"originX": 0.5,
						"originY": 0.5,
						"color": [
							1,
							1,
							1,
							1
						],
						"angle": 0,
						"zElevation": 0
					}
				},
				{
					"type": "Correct3",
					"properties": {
						"initially-visible": false,
						"initial-animation": "Animation 1",
						"initial-frame": 0,
						"enable-collisions": true,
						"live-preview": false
					},
					"uid": 424,
					"instanceVariables": {},
					"behaviors": {},
					"world": {
						"x": 955.0980545744716,
						"y": 635.4970146758856,
						"width": 290.77412600179366,
						"height": 178.99840116872474,
						"originX": 0.5,
						"originY": 0.5,
						"color": [
							1,
							1,
							1,
							1
						],
						"angle": 0,
						"zElevation": 0
					}
				},
				{
					"type": "Particles",
					"properties": {
						"rate": 100,
						"spray-cone": 60,
						"type": "one-shot",
						"object": -1,
						"live-preview": false,
						"speed": 200,
						"size": 50,
						"opacity": 100,
						"grow-rate": 0,
						"x-randomiser": 0,
						"y-randomiser": 0,
						"initial-speed-randomiser": 0,
						"size-randomiser": 0,
						"grow-rate-randomiser": 0,
						"acceleration": -150,
						"gravity": 0,
						"angle-randomiser": 0,
						"life-speed-randomiser": 800,
						"opacity-randomiser": 0,
						"destroy-mode": "fade-to-invisible",
						"timeout": 4
					},
					"uid": 425,
					"instanceVariables": {},
					"behaviors": {
						"Tween": {
							"properties": {
								"enabled": true
							}
						}
					},
					"world": {
						"x": 447,
						"y": -262,
						"width": 100,
						"height": 100,
						"originX": 0,
						"originY": 0.5,
						"color": [
							1,
							1,
							1,
							1
						],
						"angle": 0,
						"zElevation": 0
					}
				},
				{
					"type": "Particles2",
					"properties": {
						"rate": 5,
						"spray-cone": 60,
						"type": "continuous-spray",
						"object": -1,
						"live-preview": false,
						"speed": 200,
						"size": 40,
						"opacity": 100,
						"grow-rate": 0,
						"x-randomiser": 0,
						"y-randomiser": 0,
						"initial-speed-randomiser": 0,
						"size-randomiser": 0,
						"grow-rate-randomiser": 0,
						"acceleration": -150,
						"gravity": 200,
						"angle-randomiser": 0,
						"life-speed-randomiser": 800,
						"opacity-randomiser": 0,
						"destroy-mode": "fade-to-invisible",
						"timeout": 4
					},
					"uid": 426,
					"instanceVariables": {},
					"behaviors": {},
					"world": {
						"x": 1026,
						"y": -124,
						"width": 100,
						"height": 100,
						"originX": 0,
						"originY": 0.5,
						"color": [
							1,
							1,
							1,
							0
						],
						"angle": 1.5723027409065577,
						"zElevation": 0
					}
				},
				{
					"type": "Particles3",
					"properties": {
						"rate": 5,
						"spray-cone": 60,
						"type": "continuous-spray",
						"object": -1,
						"live-preview": false,
						"speed": 200,
						"size": 50,
						"opacity": 100,
						"grow-rate": 0,
						"x-randomiser": 0,
						"y-randomiser": 0,
						"initial-speed-randomiser": 0,
						"size-randomiser": 0,
						"grow-rate-randomiser": 0,
						"acceleration": -150,
						"gravity": 200,
						"angle-randomiser": 0,
						"life-speed-randomiser": 800,
						"opacity-randomiser": 0,
						"destroy-mode": "fade-to-invisible",
						"timeout": 4
					},
					"uid": 427,
					"instanceVariables": {},
					"behaviors": {},
					"world": {
						"x": 925,
						"y": -118,
						"width": 100,
						"height": 100,
						"originX": 0,
						"originY": 0.5,
						"color": [
							1,
							1,
							1,
							0
						],
						"angle": 1.5723027409065577,
						"zElevation": 0
					}
				},
				{
					"type": "Particles4",
					"properties": {
						"rate": 5,
						"spray-cone": 60,
						"type": "continuous-spray",
						"object": -1,
						"live-preview": false,
						"speed": 200,
						"size": 50,
						"opacity": 100,
						"grow-rate": 0,
						"x-randomiser": 0,
						"y-randomiser": 0,
						"initial-speed-randomiser": 0,
						"size-randomiser": 0,
						"grow-rate-randomiser": 0,
						"acceleration": -150,
						"gravity": 200,
						"angle-randomiser": 0,
						"life-speed-randomiser": 800,
						"opacity-randomiser": 0,
						"destroy-mode": "fade-to-invisible",
						"timeout": 4
					},
					"uid": 428,
					"instanceVariables": {},
					"behaviors": {},
					"world": {
						"x": 1116,
						"y": -119,
						"width": 100,
						"height": 100,
						"originX": 0,
						"originY": 0.5,
						"color": [
							1,
							1,
							1,
							0
						],
						"angle": 1.5723027409065577,
						"zElevation": 0
					}
				},
				{
					"type": "Particles5",
					"properties": {
						"rate": 5,
						"spray-cone": 60,
						"type": "continuous-spray",
						"object": -1,
						"live-preview": false,
						"speed": 200,
						"size": 50,
						"opacity": 100,
						"grow-rate": 0,
						"x-randomiser": 0,
						"y-randomiser": 0,
						"initial-speed-randomiser": 0,
						"size-randomiser": 0,
						"grow-rate-randomiser": 0,
						"acceleration": -150,
						"gravity": 200,
						"angle-randomiser": 0,
						"life-speed-randomiser": 800,
						"opacity-randomiser": 0,
						"destroy-mode": "fade-to-invisible",
						"timeout": 4
					},
					"uid": 429,
					"instanceVariables": {},
					"behaviors": {},
					"world": {
						"x": 1224,
						"y": -112,
						"width": 100,
						"height": 100,
						"originX": 0,
						"originY": 0.5,
						"color": [
							1,
							1,
							1,
							0
						],
						"angle": 1.5723027409065577,
						"zElevation": 0
					}
				},
				{
					"type": "Particles6",
					"properties": {
						"rate": 5,
						"spray-cone": 60,
						"type": "continuous-spray",
						"object": -1,
						"live-preview": false,
						"speed": 200,
						"size": 50,
						"opacity": 100,
						"grow-rate": 0,
						"x-randomiser": 0,
						"y-randomiser": 0,
						"initial-speed-randomiser": 0,
						"size-randomiser": 0,
						"grow-rate-randomiser": 0,
						"acceleration": -150,
						"gravity": 200,
						"angle-randomiser": 0,
						"life-speed-randomiser": 800,
						"opacity-randomiser": 0,
						"destroy-mode": "fade-to-invisible",
						"timeout": 4
					},
					"uid": 430,
					"instanceVariables": {},
					"behaviors": {},
					"world": {
						"x": 1326,
						"y": -106,
						"width": 100,
						"height": 100,
						"originX": 0,
						"originY": 0.5,
						"color": [
							1,
							1,
							1,
							0
						],
						"angle": 1.5723027409065577,
						"zElevation": 0
					}
				},
				{
					"type": "Particles7",
					"properties": {
						"rate": 5,
						"spray-cone": 60,
						"type": "continuous-spray",
						"object": -1,
						"live-preview": false,
						"speed": 200,
						"size": 40,
						"opacity": 100,
						"grow-rate": 0,
						"x-randomiser": 0,
						"y-randomiser": 0,
						"initial-speed-randomiser": 0,
						"size-randomiser": 0,
						"grow-rate-randomiser": 0,
						"acceleration": -150,
						"gravity": 200,
						"angle-randomiser": 0,
						"life-speed-randomiser": 800,
						"opacity-randomiser": 0,
						"destroy-mode": "fade-to-invisible",
						"timeout": 4
					},
					"uid": 431,
					"instanceVariables": {},
					"behaviors": {},
					"world": {
						"x": 835,
						"y": -110,
						"width": 100,
						"height": 100,
						"originX": 0,
						"originY": 0.5,
						"color": [
							1,
							1,
							1,
							0
						],
						"angle": 1.5723027409065577,
						"zElevation": 0
					}
				},
				{
					"type": "Particles8",
					"properties": {
						"rate": 5,
						"spray-cone": 60,
						"type": "continuous-spray",
						"object": -1,
						"live-preview": false,
						"speed": 200,
						"size": 40,
						"opacity": 100,
						"grow-rate": 0,
						"x-randomiser": 0,
						"y-randomiser": 0,
						"initial-speed-randomiser": 0,
						"size-randomiser": 0,
						"grow-rate-randomiser": 0,
						"acceleration": -150,
						"gravity": 200,
						"angle-randomiser": 0,
						"life-speed-randomiser": 800,
						"opacity-randomiser": 0,
						"destroy-mode": "fade-to-invisible",
						"timeout": 4
					},
					"uid": 432,
					"instanceVariables": {},
					"behaviors": {},
					"world": {
						"x": 738,
						"y": -114,
						"width": 100,
						"height": 100,
						"originX": 0,
						"originY": 0.5,
						"color": [
							1,
							1,
							1,
							0
						],
						"angle": 1.5723027409065577,
						"zElevation": 0
					}
				},
				{
					"type": "Particles9",
					"properties": {
						"rate": 5,
						"spray-cone": 60,
						"type": "continuous-spray",
						"object": -1,
						"live-preview": false,
						"speed": 200,
						"size": 50,
						"opacity": 100,
						"grow-rate": 0,
						"x-randomiser": 0,
						"y-randomiser": 0,
						"initial-speed-randomiser": 0,
						"size-randomiser": 0,
						"grow-rate-randomiser": 0,
						"acceleration": -150,
						"gravity": 200,
						"angle-randomiser": 0,
						"life-speed-randomiser": 800,
						"opacity-randomiser": 0,
						"destroy-mode": "fade-to-invisible",
						"timeout": 4
					},
					"uid": 433,
					"instanceVariables": {},
					"behaviors": {},
					"world": {
						"x": 644,
						"y": -113,
						"width": 100,
						"height": 100,
						"originX": 0,
						"originY": 0.5,
						"color": [
							1,
							1,
							1,
							0
						],
						"angle": 1.5723027409065577,
						"zElevation": 0
					}
				},
				{
					"type": "Correct4",
					"properties": {
						"initially-visible": false,
						"initial-animation": "Animation 1",
						"initial-frame": 0,
						"enable-collisions": true,
						"live-preview": false
					},
					"uid": 443,
					"instanceVariables": {},
					"behaviors": {},
					"world": {
						"x": 1374.9313046193367,
						"y": 637.6917917610533,
						"width": 289.1903329252641,
						"height": 174.14970262740644,
						"originX": 0.5,
						"originY": 0.5,
						"color": [
							1,
							1,
							1,
							1
						],
						"angle": 0,
						"zElevation": 0
					}
				},
				{
					"type": "logo",
					"properties": {
						"initially-visible": true,
						"initial-animation": "Animation 1",
						"initial-frame": 0,
						"enable-collisions": true,
						"live-preview": false
					},
					"uid": 13,
					"instanceVariables": {},
					"behaviors": {
						"Tween": {
							"properties": {
								"enabled": true
							}
						}
					},
					"world": {
						"x": 960,
						"y": 150,
						"width": 370,
						"height": 132,
						"originX": 0.5,
						"originY": 0.5,
						"color": [
							1,
							1,
							1,
							1
						],
						"angle": 0,
						"zElevation": 0
					}
				},
				{
					"type": "instruction",
					"properties": {
						"initially-visible": true,
						"initial-animation": "Animation 1",
						"initial-frame": 0,
						"enable-collisions": true,
						"live-preview": false
					},
					"uid": 29,
					"instanceVariables": {},
					"behaviors": {
						"Tween": {
							"properties": {
								"enabled": true
							}
						}
					},
					"world": {
						"x": 960,
						"y": 300,
						"width": 686,
						"height": 104,
						"originX": 0.5,
						"originY": 0.5,
						"color": [
							1,
							1,
							1,
							1
						],
						"angle": 0,
						"zElevation": 0
					}
				}
			],
			"sid": 792131197183831,
			"effectTypes": [],
			"isInitiallyVisible": true,
			"isInitiallyInteractive": true,
			"color": [
				1,
				1,
				1,
				1
			],
			"backgroundColor": [
				1,
				1,
				1,
				1
			],
			"isTransparent": false,
			"parallaxX": 1,
			"parallaxY": 1,
			"scaleRate": 1,
			"forceOwnTexture": false,
			"renderingMode": "3d",
			"drawOrder": "z-order",
			"useRenderCells": false,
			"blendMode": "normal",
			"zElevation": 0,
			"global": false
		},
		{
			"name": "Control",
			"overriden": 0,
			"subLayers": [],
			"instances": [
				{
					"type": "homebtn",
					"properties": {
						"initially-visible": true,
						"initial-animation": "Animation 1",
						"initial-frame": 0,
						"enable-collisions": true,
						"live-preview": false
					},
					"uid": 410,
					"instanceVariables": {},
					"behaviors": {
						"Tween": {
							"properties": {
								"enabled": true
							}
						}
					},
					"world": {
						"x": 120,
						"y": 86,
						"width": 221,
						"height": 142,
						"originX": 0.5,
						"originY": 0.5,
						"color": [
							1,
							1,
							1,
							1
						],
						"angle": 0,
						"zElevation": 0
					}
				},
				{
					"type": "hint",
					"properties": {
						"initially-visible": true,
						"initial-animation": "Animation 1",
						"initial-frame": 0,
						"enable-collisions": true,
						"live-preview": false
					},
					"uid": 412,
					"instanceVariables": {},
					"behaviors": {
						"Tween": {
							"properties": {
								"enabled": true
							}
						}
					},
					"world": {
						"x": 1809,
						"y": 86,
						"width": 200,
						"height": 140,
						"originX": 0.5,
						"originY": 0.5,
						"color": [
							1,
							1,
							1,
							1
						],
						"angle": 0,
						"zElevation": 0
					}
				},
				{
					"type": "continue",
					"properties": {
						"initially-visible": true,
						"initial-animation": "Animation 1",
						"initial-frame": 0,
						"enable-collisions": true,
						"live-preview": false
					},
					"uid": 441,
					"instanceVariables": {},
					"behaviors": {
						"Tween": {
							"properties": {
								"enabled": true
							}
						}
					},
					"world": {
						"x": 1805,
						"y": 981,
						"width": 200,
						"height": 140,
						"originX": 0.5,
						"originY": 0.5,
						"color": [
							1,
							1,
							1,
							1
						],
						"angle": 0,
						"zElevation": 0
					}
				},
				{
					"type": "tryagain",
					"properties": {
						"initially-visible": true,
						"initial-animation": "Animation 1",
						"initial-frame": 0,
						"enable-collisions": true,
						"live-preview": false
					},
					"uid": 440,
					"instanceVariables": {},
					"behaviors": {
						"Tween": {
							"properties": {
								"enabled": true
							}
						}
					},
					"world": {
						"x": 1805,
						"y": 981,
						"width": 200,
						"height": 140,
						"originX": 0.5,
						"originY": 0.5,
						"color": [
							1,
							1,
							1,
							1
						],
						"angle": 0,
						"zElevation": 0
					}
				},
				{
					"type": "next",
					"properties": {
						"initially-visible": true,
						"initial-animation": "Animation 1",
						"initial-frame": 0,
						"enable-collisions": true,
						"live-preview": false
					},
					"uid": 435,
					"instanceVariables": {},
					"behaviors": {
						"Tween": {
							"properties": {
								"enabled": true
							}
						},
						"Sine": {
							"properties": {
								"movement": "opacity",
								"wave": "sine",
								"period": 2,
								"period-random": 0,
								"period-offset": 0,
								"period-offset-random": 0,
								"magnitude": 50,
								"magnitude-random": 0,
								"enabled": false,
								"live-preview": false
							}
						}
					},
					"world": {
						"x": 1805,
						"y": 981,
						"width": 200,
						"height": 140,
						"originX": 0.5,
						"originY": 0.5,
						"color": [
							1,
							1,
							1,
							1
						],
						"angle": 0,
						"zElevation": 0
					}
				},
				{
					"type": "audiobtn",
					"properties": {
						"initially-visible": true,
						"initial-animation": "Animation 1",
						"initial-frame": 0,
						"enable-collisions": true,
						"live-preview": false
					},
					"uid": 256,
					"instanceVariables": {},
					"behaviors": {
						"Tween": {
							"properties": {
								"enabled": true
							}
						}
					},
					"world": {
						"x": 1805,
						"y": 260,
						"width": 200,
						"height": 140,
						"originX": 0.5,
						"originY": 0.5,
						"color": [
							1,
							1,
							1,
							1
						],
						"angle": 0,
						"zElevation": 0
					}
				},
				{
					"type": "showanswer",
					"properties": {
						"initially-visible": true,
						"initial-animation": "Animation 1",
						"initial-frame": 0,
						"enable-collisions": true,
						"live-preview": false
					},
					"uid": 328,
					"instanceVariables": {},
					"behaviors": {
						"Tween": {
							"properties": {
								"enabled": true
							}
						}
					},
					"world": {
						"x": 1805,
						"y": 981,
						"width": 200,
						"height": 140,
						"originX": 0.5,
						"originY": 0.5,
						"color": [
							1,
							1,
							1,
							1
						],
						"angle": 0,
						"zElevation": 0
					}
				}
			],
			"sid": 919464512796620,
			"effectTypes": [],
			"isInitiallyVisible": true,
			"isInitiallyInteractive": true,
			"color": [
				1,
				1,
				1,
				1
			],
			"backgroundColor": [
				0.3686274509803922,
				0.3686274509803922,
				0.3686274509803922,
				1
			],
			"isTransparent": true,
			"parallaxX": 1,
			"parallaxY": 1,
			"scaleRate": 1,
			"forceOwnTexture": false,
			"renderingMode": "3d",
			"drawOrder": "z-order",
			"useRenderCells": false,
			"blendMode": "normal",
			"zElevation": 0,
			"global": false
		},
		{
			"name": "Detectors",
			"overriden": 0,
			"subLayers": [],
			"instances": [
				{
					"type": "b",
					"properties": {
						"initially-visible": true,
						"initial-animation": "Animation 1",
						"initial-frame": 0,
						"enable-collisions": true,
						"live-preview": false
					},
					"uid": 420,
					"instanceVariables": {
						"plus": 0
					},
					"behaviors": {},
					"world": {
						"x": 551.0259019895923,
						"y": 504.5752823561445,
						"width": 180.17094315673194,
						"height": -57,
						"originX": 0.5,
						"originY": 0.5,
						"color": [
							1,
							1,
							1,
							1
						],
						"angle": 0,
						"zElevation": 0
					}
				},
				{
					"type": "c",
					"properties": {
						"initially-visible": true,
						"initial-animation": "Animation 1",
						"initial-frame": 0,
						"enable-collisions": true,
						"live-preview": false
					},
					"uid": 421,
					"instanceVariables": {
						"plus": 0
					},
					"behaviors": {},
					"world": {
						"x": 949.569848958603,
						"y": 507.459901299536,
						"width": 185.44393657474973,
						"height": -56,
						"originX": 0.5,
						"originY": 0.5,
						"color": [
							1,
							1,
							1,
							1
						],
						"angle": 0,
						"zElevation": 0
					}
				},
				{
					"type": "d",
					"properties": {
						"initially-visible": true,
						"initial-animation": "Animation 1",
						"initial-frame": 0,
						"enable-collisions": true,
						"live-preview": false
					},
					"uid": 442,
					"instanceVariables": {},
					"behaviors": {},
					"world": {
						"x": 1369.935629336145,
						"y": 504.3925861487884,
						"width": 189.6190573106153,
						"height": 59.09650755313032,
						"originX": 0.5,
						"originY": 0.5,
						"color": [
							1,
							1,
							1,
							1
						],
						"angle": 0,
						"zElevation": 0
					}
				}
			],
			"sid": 213838813859999,
			"effectTypes": [],
			"isInitiallyVisible": true,
			"isInitiallyInteractive": true,
			"color": [
				1,
				1,
				1,
				1
			],
			"backgroundColor": [
				0.3686274509803922,
				0.3686274509803922,
				0.3686274509803922,
				1
			],
			"isTransparent": true,
			"parallaxX": 1,
			"parallaxY": 1,
			"scaleRate": 1,
			"forceOwnTexture": false,
			"renderingMode": "3d",
			"drawOrder": "z-order",
			"useRenderCells": false,
			"blendMode": "normal",
			"zElevation": 0,
			"global": false
		},
		{
			"name": "Interactables",
			"overriden": 0,
			"subLayers": [],
			"instances": [
				{
					"type": "Awindy",
					"properties": {
						"initially-visible": false,
						"initial-animation": "Animation 1",
						"initial-frame": 0,
						"enable-collisions": true,
						"live-preview": false
					},
					"uid": 418,
					"instanceVariables": {},
					"behaviors": {
						"Tween": {
							"properties": {
								"enabled": true
							}
						}
					},
					"world": {
						"x": 543.1800326941416,
						"y": 498.9119829928362,
						"width": 209.37527408972207,
						"height": 56.46374922693474,
						"originX": 0.5,
						"originY": 0.5,
						"color": [
							1,
							1,
							1,
							1
						],
						"angle": 0,
						"zElevation": 0
					}
				},
				{
					"type": "Arainy",
					"properties": {
						"initially-visible": false,
						"initial-animation": "Animation 1",
						"initial-frame": 0,
						"enable-collisions": true,
						"live-preview": false
					},
					"uid": 444,
					"instanceVariables": {},
					"behaviors": {
						"Tween": {
							"properties": {
								"enabled": true
							}
						}
					},
					"world": {
						"x": 942.2860960125171,
						"y": 501.87324222871723,
						"width": 199.74664871582115,
						"height": 56.133109082139356,
						"originX": 0.5,
						"originY": 0.5,
						"color": [
							1,
							1,
							1,
							1
						],
						"angle": 0,
						"zElevation": 0
					}
				},
				{
					"type": "Asnowy",
					"properties": {
						"initially-visible": false,
						"initial-animation": "Animation 1",
						"initial-frame": 0,
						"enable-collisions": true,
						"live-preview": false
					},
					"uid": 445,
					"instanceVariables": {},
					"behaviors": {
						"Tween": {
							"properties": {
								"enabled": true
							}
						}
					},
					"world": {
						"x": 1363.335091208057,
						"y": 498.02510546118083,
						"width": 199.73094588264394,
						"height": 64.20272646782729,
						"originX": 0.5,
						"originY": 0.5,
						"color": [
							1,
							1,
							1,
							1
						],
						"angle": 0,
						"zElevation": 0
					}
				},
				{
					"type": "rainy",
					"properties": {
						"initially-visible": true,
						"initial-animation": "Animation 1",
						"initial-frame": 0,
						"enable-collisions": true,
						"live-preview": false
					},
					"uid": 436,
					"instanceVariables": {},
					"behaviors": {
						"Tween": {
							"properties": {
								"enabled": true
							}
						},
						"DragDrop": {
							"properties": {
								"axes": "both",
								"enabled": true
							}
						}
					},
					"world": {
						"x": 631,
						"y": 890,
						"width": 201.196934377519,
						"height": 79.10985166248423,
						"originX": 0.5,
						"originY": 0.5,
						"color": [
							1,
							1,
							1,
							1
						],
						"angle": 0.0005840039184641377,
						"zElevation": 0
					}
				},
				{
					"type": "windy",
					"properties": {
						"initially-visible": true,
						"initial-animation": "Animation 1",
						"initial-frame": 0,
						"enable-collisions": true,
						"live-preview": false
					},
					"uid": 437,
					"instanceVariables": {},
					"behaviors": {
						"Tween": {
							"properties": {
								"enabled": true
							}
						},
						"DragDrop": {
							"properties": {
								"axes": "both",
								"enabled": true
							}
						}
					},
					"world": {
						"x": 1265.5279358119628,
						"y": 900.3201975319465,
						"width": 155.7690264347117,
						"height": 65.43915201570663,
						"originX": 0.5,
						"originY": 0.5,
						"color": [
							1,
							1,
							1,
							1
						],
						"angle": 6.278981084164851,
						"zElevation": 0
					}
				},
				{
					"type": "cloudy",
					"properties": {
						"initially-visible": true,
						"initial-animation": "Animation 1",
						"initial-frame": 0,
						"enable-collisions": true,
						"live-preview": false
					},
					"uid": 438,
					"instanceVariables": {},
					"behaviors": {
						"Tween": {
							"properties": {
								"enabled": true
							}
						},
						"DragDrop": {
							"properties": {
								"axes": "both",
								"enabled": true
							}
						}
					},
					"world": {
						"x": 944,
						"y": 881,
						"width": 152.3924795262954,
						"height": 57.64191793271398,
						"originX": 0.5,
						"originY": 0.5,
						"color": [
							1,
							1,
							1,
							1
						],
						"angle": 0,
						"zElevation": 0
					}
				},
				{
					"type": "calm",
					"properties": {
						"initially-visible": true,
						"initial-animation": "Animation 1",
						"initial-frame": 0,
						"enable-collisions": true,
						"live-preview": false
					},
					"uid": 439,
					"instanceVariables": {},
					"behaviors": {
						"Tween": {
							"properties": {
								"enabled": true
							}
						},
						"DragDrop": {
							"properties": {
								"axes": "both",
								"enabled": true
							}
						}
					},
					"world": {
						"x": 798,
						"y": 978.5,
						"width": 176.16066814549163,
						"height": 69.29498896298081,
						"originX": 0.5,
						"originY": 0.5,
						"color": [
							1,
							1,
							1,
							1
						],
						"angle": 0,
						"zElevation": 0
					}
				},
				{
					"type": "snowy",
					"properties": {
						"initially-visible": true,
						"initial-animation": "Animation 1",
						"initial-frame": 0,
						"enable-collisions": true,
						"live-preview": false
					},
					"uid": 446,
					"instanceVariables": {},
					"behaviors": {
						"Tween": {
							"properties": {
								"enabled": true
							}
						},
						"DragDrop": {
							"properties": {
								"axes": "both",
								"enabled": true
							}
						}
					},
					"world": {
						"x": 1101,
						"y": 986,
						"width": 153.2497764628613,
						"height": 62.33732598814658,
						"originX": 0.5,
						"originY": 0.5,
						"color": [
							1,
							1,
							1,
							1
						],
						"angle": 0,
						"zElevation": 0
					}
				}
			],
			"sid": 252525575111850,
			"effectTypes": [],
			"isInitiallyVisible": true,
			"isInitiallyInteractive": true,
			"color": [
				1,
				1,
				1,
				1
			],
			"backgroundColor": [
				0.3686274509803922,
				0.3686274509803922,
				0.3686274509803922,
				1
			],
			"isTransparent": true,
			"parallaxX": 1,
			"parallaxY": 1,
			"scaleRate": 1,
			"forceOwnTexture": false,
			"renderingMode": "3d",
			"drawOrder": "z-order",
			"useRenderCells": false,
			"blendMode": "normal",
			"zElevation": 0,
			"global": false
		},
		{
			"name": "Mascot",
			"overriden": 0,
			"subLayers": [],
			"instances": [
				{
					"type": "CorrectMascot",
					"properties": {
						"initially-visible": true,
						"initial-animation": "Default",
						"initial-frame": 0,
						"enable-collisions": true,
						"live-preview": false
					},
					"uid": 300,
					"instanceVariables": {},
					"behaviors": {},
					"world": {
						"x": 959,
						"y": 837,
						"width": 500,
						"height": 500,
						"originX": 0.5,
						"originY": 0.5,
						"color": [
							1,
							1,
							1,
							1
						],
						"angle": 0,
						"zElevation": 0
					}
				},
				{
					"type": "WrongMascot",
					"properties": {
						"initially-visible": true,
						"initial-animation": "Default",
						"initial-frame": 0,
						"enable-collisions": true,
						"live-preview": false
					},
					"uid": 301,
					"instanceVariables": {},
					"behaviors": {},
					"world": {
						"x": 959,
						"y": 837,
						"width": 500,
						"height": 500,
						"originX": 0.5,
						"originY": 0.5,
						"color": [
							1,
							1,
							1,
							1
						],
						"angle": 0,
						"zElevation": 0
					}
				},
				{
					"type": "TryAgainText",
					"properties": {
						"initially-visible": true,
						"initial-animation": "Default",
						"initial-frame": 0,
						"enable-collisions": true,
						"live-preview": false
					},
					"uid": 314,
					"instanceVariables": {},
					"behaviors": {},
					"world": {
						"x": 1266,
						"y": 868,
						"width": 353.78356866776255,
						"height": 207.3262085355783,
						"originX": 0.5,
						"originY": 0.5,
						"color": [
							1,
							1,
							1,
							1
						],
						"angle": 0,
						"zElevation": 0
					}
				},
				{
					"type": "CorrectText",
					"properties": {
						"initially-visible": true,
						"initial-animation": "Default",
						"initial-frame": 0,
						"enable-collisions": true,
						"live-preview": false
					},
					"uid": 315,
					"instanceVariables": {},
					"behaviors": {},
					"world": {
						"x": 1268,
						"y": 860,
						"width": 307.70953835004843,
						"height": 176.7466552460486,
						"originX": 0.5,
						"originY": 0.5,
						"color": [
							1,
							1,
							1,
							1
						],
						"angle": 0,
						"zElevation": 0
					}
				},
				{
					"type": "Incorrect",
					"properties": {
						"initially-visible": true,
						"initial-animation": "Default",
						"initial-frame": 0,
						"enable-collisions": true,
						"live-preview": false
					},
					"uid": 340,
					"instanceVariables": {},
					"behaviors": {},
					"world": {
						"x": 1260,
						"y": 865,
						"width": 301.75335712446764,
						"height": 165.52489978186813,
						"originX": 0.5,
						"originY": 0.5,
						"color": [
							1,
							1,
							1,
							1
						],
						"angle": 0,
						"zElevation": 0
					}
				}
			],
			"sid": 832676502818381,
			"effectTypes": [],
			"isInitiallyVisible": true,
			"isInitiallyInteractive": true,
			"color": [
				1,
				1,
				1,
				1
			],
			"backgroundColor": [
				0.3686274509803922,
				0.3686274509803922,
				0.3686274509803922,
				1
			],
			"isTransparent": true,
			"parallaxX": 1,
			"parallaxY": 1,
			"scaleRate": 1,
			"forceOwnTexture": false,
			"renderingMode": "3d",
			"drawOrder": "z-order",
			"useRenderCells": false,
			"blendMode": "normal",
			"zElevation": 0,
			"global": false
		},
		{
			"name": "Hint",
			"overriden": 0,
			"subLayers": [],
			"instances": [
				{
					"type": "Sprite11",
					"properties": {
						"initially-visible": false,
						"initial-animation": "Animation 1",
						"initial-frame": 0,
						"enable-collisions": true,
						"live-preview": false
					},
					"uid": 286,
					"instanceVariables": {},
					"behaviors": {
						"Tween": {
							"properties": {
								"enabled": true
							}
						}
					},
					"world": {
						"x": 960,
						"y": 540,
						"width": 700,
						"height": 700,
						"originX": 0.5,
						"originY": 0.5,
						"color": [
							1,
							1,
							1,
							1
						],
						"angle": 0,
						"zElevation": 0
					}
				}
			],
			"sid": 301508856612702,
			"effectTypes": [],
			"isInitiallyVisible": true,
			"isInitiallyInteractive": true,
			"color": [
				1,
				1,
				1,
				1
			],
			"backgroundColor": [
				0.3686274509803922,
				0.3686274509803922,
				0.3686274509803922,
				1
			],
			"isTransparent": true,
			"parallaxX": 1,
			"parallaxY": 1,
			"scaleRate": 1,
			"forceOwnTexture": false,
			"renderingMode": "3d",
			"drawOrder": "z-order",
			"useRenderCells": false,
			"blendMode": "normal",
			"zElevation": 0,
			"global": false
		},
		{
			"name": "Loading",
			"overriden": 0,
			"subLayers": [],
			"instances": [
				{
					"type": "bar2",
					"properties": {
						"initially-visible": false,
						"initial-animation": "Animation 1",
						"initial-frame": 0,
						"enable-collisions": true,
						"live-preview": false
					},
					"uid": 407,
					"instanceVariables": {},
					"behaviors": {
						"Sine": {
							"properties": {
								"movement": "height",
								"wave": "sine",
								"period": 0.8,
								"period-random": 0,
								"period-offset": 0,
								"period-offset-random": 0,
								"magnitude": 100,
								"magnitude-random": 0,
								"enabled": true,
								"live-preview": false
							}
						},
						"Sine2": {
							"properties": {
								"movement": "opacity",
								"wave": "sine",
								"period": 1.5,
								"period-random": 0,
								"period-offset": 0,
								"period-offset-random": 0,
								"magnitude": 50,
								"magnitude-random": 0,
								"enabled": true,
								"live-preview": false
							}
						}
					},
					"world": {
						"x": 960,
						"y": 540,
						"width": 75,
						"height": 220,
						"originX": 0.5,
						"originY": 0.5,
						"color": [
							1,
							1,
							1,
							1
						],
						"angle": 0,
						"zElevation": 0
					}
				},
				{
					"type": "bar1",
					"properties": {
						"initially-visible": false,
						"initial-animation": "Animation 1",
						"initial-frame": 0,
						"enable-collisions": true,
						"live-preview": false
					},
					"uid": 408,
					"instanceVariables": {},
					"behaviors": {
						"Sine": {
							"properties": {
								"movement": "height",
								"wave": "sine",
								"period": 1,
								"period-random": 0,
								"period-offset": 0,
								"period-offset-random": 0,
								"magnitude": 50,
								"magnitude-random": 0,
								"enabled": true,
								"live-preview": false
							}
						},
						"Sine2": {
							"properties": {
								"movement": "opacity",
								"wave": "sine",
								"period": 1,
								"period-random": 0,
								"period-offset": 0,
								"period-offset-random": 0,
								"magnitude": 50,
								"magnitude-random": 0,
								"enabled": true,
								"live-preview": false
							}
						}
					},
					"world": {
						"x": 860,
						"y": 540,
						"width": 70,
						"height": 159,
						"originX": 0.5,
						"originY": 0.5,
						"color": [
							1,
							1,
							1,
							1
						],
						"angle": 0,
						"zElevation": 0
					}
				},
				{
					"type": "bar3",
					"properties": {
						"initially-visible": false,
						"initial-animation": "Animation 1",
						"initial-frame": 0,
						"enable-collisions": true,
						"live-preview": false
					},
					"uid": 409,
					"instanceVariables": {},
					"behaviors": {
						"Sine": {
							"properties": {
								"movement": "height",
								"wave": "sine",
								"period": 1.2,
								"period-random": 0,
								"period-offset": 0,
								"period-offset-random": 0,
								"magnitude": 150,
								"magnitude-random": 0,
								"enabled": true,
								"live-preview": false
							}
						},
						"Sine2": {
							"properties": {
								"movement": "opacity",
								"wave": "sine",
								"period": 0.5,
								"period-random": 0,
								"period-offset": 0,
								"period-offset-random": 0,
								"magnitude": 50,
								"magnitude-random": 0,
								"enabled": true,
								"live-preview": false
							}
						}
					},
					"world": {
						"x": 1060,
						"y": 540,
						"width": 75,
						"height": 300,
						"originX": 0.5,
						"originY": 0.5,
						"color": [
							1,
							1,
							1,
							1
						],
						"angle": 0,
						"zElevation": 0
					}
				}
			],
			"sid": 648535571049502,
			"effectTypes": [],
			"isInitiallyVisible": true,
			"isInitiallyInteractive": true,
			"color": [
				1,
				1,
				1,
				1
			],
			"backgroundColor": [
				0.3686274509803922,
				0.3686274509803922,
				0.3686274509803922,
				1
			],
			"isTransparent": true,
			"parallaxX": 1,
			"parallaxY": 1,
			"scaleRate": 1,
			"forceOwnTexture": false,
			"renderingMode": "3d",
			"drawOrder": "z-order",
			"useRenderCells": false,
			"blendMode": "normal",
			"zElevation": 0,
			"global": false
		},
		{
			"name": "Fader",
			"overriden": 0,
			"subLayers": [],
			"instances": [
				{
					"type": "fader",
					"properties": {
						"initially-visible": true,
						"initial-animation": "Animation 1",
						"initial-frame": 0,
						"enable-collisions": true,
						"live-preview": false
					},
					"uid": 237,
					"instanceVariables": {},
					"behaviors": {
						"Tween": {
							"properties": {
								"enabled": true
							}
						}
					},
					"world": {
						"x": 965,
						"y": 544.5,
						"width": 1969,
						"height": 1121,
						"originX": 0.5,
						"originY": 0.5,
						"color": [
							1,
							1,
							1,
							1
						],
						"angle": 0,
						"zElevation": 0
					}
				}
			],
			"sid": 247238543063857,
			"effectTypes": [],
			"isInitiallyVisible": true,
			"isInitiallyInteractive": true,
			"color": [
				1,
				1,
				1,
				1
			],
			"backgroundColor": [
				0.3686274509803922,
				0.3686274509803922,
				0.3686274509803922,
				1
			],
			"isTransparent": true,
			"parallaxX": 1,
			"parallaxY": 1,
			"scaleRate": 1,
			"forceOwnTexture": false,
			"renderingMode": "3d",
			"drawOrder": "z-order",
			"useRenderCells": false,
			"blendMode": "normal",
			"zElevation": 0,
			"global": false
		},
		{
			"name": "Language",
			"overriden": 0,
			"subLayers": [],
			"instances": [
				{
					"type": "fader",
					"properties": {
						"initially-visible": true,
						"initial-animation": "Animation 1",
						"initial-frame": 0,
						"enable-collisions": true,
						"live-preview": false
					},
					"uid": 447,
					"instanceVariables": {},
					"behaviors": {
						"Tween": {
							"properties": {
								"enabled": true
							}
						}
					},
					"world": {
						"x": 351,
						"y": 991,
						"width": 2817,
						"height": 1999.9999999999998,
						"originX": 0.5,
						"originY": 0.5,
						"color": [
							1,
							1,
							1,
							0
						],
						"angle": 0,
						"zElevation": 0
					}
				}
			],
			"sid": 338956790796509,
			"effectTypes": [],
			"isInitiallyVisible": false,
			"isInitiallyInteractive": true,
			"color": [
				1,
				1,
				1,
				1
			],
			"backgroundColor": [
				1,
				1,
				1,
				1
			],
			"isTransparent": true,
			"parallaxX": 1,
			"parallaxY": 1,
			"scaleRate": 1,
			"forceOwnTexture": false,
			"renderingMode": "3d",
			"drawOrder": "z-order",
			"useRenderCells": false,
			"blendMode": "normal",
			"zElevation": 0,
			"global": false
		}
	],
	"sid": 616721235437223,
	"nonworld-instances": [],
	"effectTypes": [],
	"width": 3840,
	"height": 2160,
	"unboundedScrolling": true,
	"vpX": 0.5,
	"vpY": 0.5,
	"projection": "perspective",
	"eventSheet": "Activity4_ES"
}